lfc_blog
